<annotation>
  <folder>VOC2007</folder>
  <filename>5ABF360003A0FF_TDI_D0366G0990_O1_PXL9_PI800_NON_PI800_NON_PI800.jpg</filename>
  <path>5ABF360003A0FF_TDI_D0366G0990_O1_PXL9_PI800_NON_PI800_NON_PI800.jpg</path>
  <source>
    <database>Unknown</database>
  </source>
  <size>
    <width>64</width>
    <height>64</height>
    <depth>1</depth>
  </size>
  <segmented>0</segmented>
  <object>
    <name>dust</name>
    <pose>Unspecified</pose>
    <truncated>0</truncated>
    <difficult>0</difficult>
    <bndbox>
      <xmin>19</xmin>
      <ymin>56</ymin>
      <xmax>24</xmax>
      <ymax>59</ymax>
    </bndbox>
  </object>
</annotation>
