<annotation>
  <folder>VOC2007</folder>
  <filename>5AEK520043B3AG_TDI_X84.547Y1071.775_PXL8_SD013_AI_PXL8_SD013.jpg</filename>
  <path>5AEK520043B3AG_TDI_X84.547Y1071.775_PXL8_SD013_AI_PXL8_SD013.jpg</path>
  <source>
    <database>Unknown</database>
  </source>
  <size>
    <width>64</width>
    <height>64</height>
    <depth>1</depth>
  </size>
  <segmented>0</segmented>
  <object>
    <name>dust</name>
    <pose>Unspecified</pose>
    <truncated>0</truncated>
    <difficult>0</difficult>
    <bndbox>
      <xmin>31</xmin>
      <ymin>29</ymin>
      <xmax>34</xmax>
      <ymax>32</ymax>
    </bndbox>
  </object>
  <object>
    <name>dust</name>
    <pose>Unspecified</pose>
    <truncated>0</truncated>
    <difficult>0</difficult>
    <bndbox>
      <xmin>2</xmin>
      <ymin>17</ymin>
      <xmax>5</xmax>
      <ymax>20</ymax>
    </bndbox>
  </object>
</annotation>
